LICENSE
MANIFEST.in
pavement.py
paver-minilib.zip
prctlmodule.c
setup.py
prctl.egg-info/PKG-INFO
prctl.egg-info/SOURCES.txt
prctl.egg-info/dependency_links.txt
prctl.egg-info/top_level.txt